README.rst
setup.py
dekigokoro/dekigokoro.py
dekigokoro.egg-info/PKG-INFO
dekigokoro.egg-info/SOURCES.txt
dekigokoro.egg-info/dependency_links.txt
dekigokoro.egg-info/requires.txt
dekigokoro.egg-info/top_level.txt
dekigokoro/utils/values.py